blastpipe/__init__.pyc
blastpipe/__init__.pyi
blastpipe/backports.pyc
blastpipe/backports.pyi
blastpipe/buffer.pyc
blastpipe/buffer.pyi
blastpipe/loop.pyc
blastpipe/loop.pyi
blastpipe/malloc.pyc
blastpipe/malloc.pyi
blastpipe/mixin.pyc
blastpipe/mixin.pyi
blastpipe/py.typed
blastpipe/sequence.pyc
blastpipe/sequence.pyi
blastpipe/tailcall.pyc
blastpipe/tailcall.pyi
blastpipe/tests/test_backports.pyc
blastpipe/tests/test_fuzz.pyc
blastpipe/tests/test_tailcall.pyc
msgspec/__init__.pyc
msgspec/__init__.pyi
msgspec/_core.c
msgspec/_core.cpython-313-x86_64-linux-musl.so
msgspec/_json_schema.pyc
msgspec/_utils.pyc
msgspec/atof.h
msgspec/atof_consts.h
msgspec/common.h
msgspec/inspect.pyc
msgspec/itoa.h
msgspec/json.pyc
msgspec/json.pyi
msgspec/msgpack.pyc
msgspec/msgpack.pyi
msgspec/py.typed
msgspec/ryu.h
msgspec/structs.pyc
msgspec/structs.pyi
msgspec/toml.pyc
msgspec/yaml.pyc
msgspec/tests/basic_typing_examples.pyc
msgspec/tests/conftest.pyc
msgspec/tests/test_JSONTestSuite.pyc
msgspec/tests/test_common.pyc
msgspec/tests/test_constraints.pyc
msgspec/tests/test_convert.pyc
msgspec/tests/test_cpylint.pyc
msgspec/tests/test_inspect.pyc
msgspec/tests/test_integration.pyc
msgspec/tests/test_json.pyc
msgspec/tests/test_msgpack.pyc
msgspec/tests/test_mypy.pyc
msgspec/tests/test_performance.pyc
msgspec/tests/test_pyright.pyc
msgspec/tests/test_raw.pyc
msgspec/tests/test_schema.pyc
msgspec/tests/test_struct.pyc
msgspec/tests/test_to_builtins.pyc
msgspec/tests/test_toml.pyc
msgspec/tests/test_utils.pyc
msgspec/tests/test_yaml.pyc
msgspec/tests/utils.pyc
blastpipe-2025.0.2.dist-info/LICENSE.txt
blastpipe-2025.0.2.dist-info/METADATA
blastpipe-2025.0.2.dist-info/WHEEL
blastpipe-2025.0.2.dist-info/RECORD
